robotframework_historic/__init__.py
robotframework_historic/app.py
robotframework_historic/args.py
robotframework_historic/parserargs.py
robotframework_historic/rfhistoricparser.py
robotframework_historic/rfhistoricsetup.py
robotframework_historic/rfhistoricupdate.py
robotframework_historic/setupargs.py
robotframework_historic/updateargs.py
robotframework_historic/templates/comment.html
robotframework_historic/templates/compare.html
robotframework_historic/templates/dashboardAll.html
robotframework_historic/templates/dashboardByEid.html
robotframework_historic/templates/dashboardRecent.html
robotframework_historic/templates/dashboardRecentFive.html
robotframework_historic/templates/dashboardRecentTen.html
robotframework_historic/templates/dashboardRecentThirty.html
robotframework_historic/templates/deldbconf.html
robotframework_historic/templates/deleconf.html
robotframework_historic/templates/ehistoric.html
robotframework_historic/templates/eidtmetrics.html
robotframework_historic/templates/failures.html
robotframework_historic/templates/flaky.html
robotframework_historic/templates/home.html
robotframework_historic/templates/metrics.html
robotframework_historic/templates/newdb.html
robotframework_historic/templates/query.html
robotframework_historic/templates/redirect.html
robotframework_historic/templates/search.html
robotframework_historic/templates/tmetrics.html
robotframework_historic/templates/ttags.html
robotframework_historic/templates/updatedb.html
robotframework_historic/templates/assets/css/dashboard.css
robotframework_historic/templates/assets/fonts/feather/feather-webfont.eot
robotframework_historic/templates/assets/fonts/feather/feather-webfont.svg
robotframework_historic/templates/assets/fonts/feather/feather-webfont.ttf
robotframework_historic/templates/assets/fonts/feather/feather-webfont.woff
robotframework_historic/templates/assets/js/core.js
robotframework_historic/templates/assets/js/dashboard.js
robotframework_historic-0.2.8.dist-info/LICENSE
robotframework_historic-0.2.8.dist-info/METADATA
robotframework_historic-0.2.8.dist-info/WHEEL
robotframework_historic-0.2.8.dist-info/entry_points.txt
robotframework_historic-0.2.8.dist-info/top_level.txt
robotframework_historic-0.2.8.dist-info/RECORD
